README.rst
s3io.py
setup.py
s3io.egg-info/PKG-INFO
s3io.egg-info/SOURCES.txt
s3io.egg-info/dependency_links.txt
s3io.egg-info/requires.txt
s3io.egg-info/top_level.txt