Metadata-Version: 1.1
Name: s3io
Version: 0.1.0
Summary: Access resources on Amazon S3 as a File Object.
Home-page: https://github.com/malexer/s3io
Author: Alex Markov
Author-email: alex@markovs.me
License: MIT
Keywords: amazon aws s3 file
Platform: UNKNOWN
Classifier: Development Status :: 4 - Beta
Classifier: Intended Audience :: Developers
Classifier: Topic :: Software Development :: Libraries :: Python Modules
Classifier: License :: OSI Approved :: MIT License
Classifier: Programming Language :: Python :: 2
Classifier: Programming Language :: Python :: 2.6
Classifier: Programming Language :: Python :: 2.7
Classifier: Programming Language :: Python :: 3
Classifier: Programming Language :: Python :: 3.2
Classifier: Programming Language :: Python :: 3.3
Classifier: Programming Language :: Python :: 3.4
